spiketoolkit/__init__.py
spiketoolkit/utils.py
spiketoolkit/version.py
spiketoolkit/curation/__init__.py
spiketoolkit/curation/threshold_metrics.py
spiketoolkit/postprocessing/__init__.py
spiketoolkit/postprocessing/features.py
spiketoolkit/postprocessing/postprocessing_tools.py
spiketoolkit/postprocessing/utils.py
spiketoolkit/preprocessing/__init__.py
spiketoolkit/preprocessing/bandpass_filter.py
spiketoolkit/preprocessing/basepreprocessorrecording.py
spiketoolkit/preprocessing/blank_saturation.py
spiketoolkit/preprocessing/center.py
spiketoolkit/preprocessing/clip.py
spiketoolkit/preprocessing/common_reference.py
spiketoolkit/preprocessing/filterrecording.py
spiketoolkit/preprocessing/highpass_filter.py
spiketoolkit/preprocessing/mask.py
spiketoolkit/preprocessing/normalize_by_quantile.py
spiketoolkit/preprocessing/notch_filter.py
spiketoolkit/preprocessing/preprocessinglist.py
spiketoolkit/preprocessing/rectify.py
spiketoolkit/preprocessing/remove_artifacts.py
spiketoolkit/preprocessing/remove_bad_channels.py
spiketoolkit/preprocessing/resample.py
spiketoolkit/preprocessing/transform.py
spiketoolkit/preprocessing/whiten.py
spiketoolkit/sortingcomponents/__init__.py
spiketoolkit/sortingcomponents/detection.py
spiketoolkit/tests/__init__.py
spiketoolkit/tests/test_curation.py
spiketoolkit/tests/test_curation_extractor.py
spiketoolkit/tests/test_postprocessing.py
spiketoolkit/tests/test_preprocessing.py
spiketoolkit/tests/test_sortingcomponents.py
spiketoolkit/tests/test_validation.py
spiketoolkit/tests/utils.py
spiketoolkit/validation/__init__.py
spiketoolkit/validation/curation_list.py
spiketoolkit/validation/quality_metrics.py
spiketoolkit/validation/validation_list.py
spiketoolkit/validation/quality_metric_classes/__init__.py
spiketoolkit/validation/quality_metric_classes/amplitude_cutoff.py
spiketoolkit/validation/quality_metric_classes/d_prime.py
spiketoolkit/validation/quality_metric_classes/drift_metric.py
spiketoolkit-0.7.7.dist-info/LICENSE
spiketoolkit-0.7.7.dist-info/METADATA
spiketoolkit-0.7.7.dist-info/WHEEL
spiketoolkit-0.7.7.dist-info/top_level.txt
spiketoolkit-0.7.7.dist-info/RECORD
